redisy/__init__.py
redisy/__init__.pyc
redisy/converter.py
redisy/converter.pyc
redisy/redis_hash.py
redisy/redis_hash.pyc
redisy/redis_list.py
redisy/redis_list.pyc
redisy/redis_set.py
redisy/redis_set.pyc
redisy/redisy.py
redisy/redisy.pyc
redisy/__pycache__/__init__.cpython-36.pyc
redisy/__pycache__/converter.cpython-36.pyc
redisy/__pycache__/redis_hash.cpython-36.pyc
redisy/__pycache__/redis_list.cpython-36.pyc
redisy/__pycache__/redis_set.cpython-36.pyc
redisy/__pycache__/redisy.cpython-36.pyc
redisy-0.1.dist-info/DESCRIPTION.rst
redisy-0.1.dist-info/METADATA
redisy-0.1.dist-info/RECORD
redisy-0.1.dist-info/WHEEL
redisy-0.1.dist-info/metadata.json
redisy-0.1.dist-info/top_level.txt
