Metadata-Version: 2.0
Name: redisy
Version: 0.1
Summary: A higher-level python native object api based on redisy-py
Home-page: https://github.com/yytdfc/redisy
Author: yytdfc
Author-email: fuchen@foxmail.com
License: MIT
Keywords: redis,api
Platform: UNKNOWN
Classifier: Development Status :: 5 - Production/Stable
Classifier: Environment :: Console
Classifier: Intended Audience :: Developers
Classifier: Intended Audience :: System Administrators
Classifier: License :: OSI Approved :: MIT License
Classifier: Programming Language :: Python
Classifier: Programming Language :: Python :: 3.6
Classifier: Topic :: Software Development :: Build Tools
Classifier: Topic :: Software Development :: Libraries :: Python Modules
Requires-Dist: redis
